oetils/__init__.py
oetils/plotting.py
oetils/util.py
oetils-0.2.11.dist-info/LICENSE
oetils-0.2.11.dist-info/METADATA
oetils-0.2.11.dist-info/WHEEL
oetils-0.2.11.dist-info/RECORD
