Metadata-Version: 2.1
Name: oetils
Version: 0.2.11
Summary: A collection of useful functions and classes
Home-page: https://github.com/onnoeberhard/oetils
License: MIT
Author: Onno Eberhard
Author-email: onnoeberhard@gmail.com
Requires-Python: >=3.9,<4.0
Classifier: License :: OSI Approved :: MIT License
Classifier: Programming Language :: Python :: 3
Classifier: Programming Language :: Python :: 3.9
Classifier: Programming Language :: Python :: 3.10
Classifier: Programming Language :: Python :: 3.11
Classifier: Programming Language :: Python :: 3.12
Classifier: Programming Language :: Python :: 3.13
Requires-Dist: jax
Requires-Dist: matplotlib
Requires-Dist: numpy
Requires-Dist: scienceplots
Requires-Dist: scipy
Requires-Dist: tqdm
Requires-Dist: tueplots
Project-URL: Repository, https://github.com/onnoeberhard/oetils
